Metadata-Version: 1.0
Name: sample-packaging
Version: 1.1
Summary: Sample packaging
Home-page: https://github.com/kartikiyyer/sample-packaging.git
Author: Kartik
Author-email: sample@packaging.com
License: MIT
Platform: UNKNOWN
